graval/__init__.py
graval/base.py
graval/miner.py
graval/structures.py
graval/validator.py
graval/lib/libgraval-miner.so
graval/lib/libgraval-validator.so
graval-0.2.6.dist-info/METADATA
graval-0.2.6.dist-info/WHEEL
graval-0.2.6.dist-info/top_level.txt
graval-0.2.6.dist-info/RECORD
